DoorPi-2.5.1.dist-info/DESCRIPTION.rst
DoorPi-2.5.1.dist-info/METADATA
DoorPi-2.5.1.dist-info/RECORD
DoorPi-2.5.1.dist-info/WHEEL
DoorPi-2.5.1.dist-info/entry_points.txt
DoorPi-2.5.1.dist-info/metadata.json
DoorPi-2.5.1.dist-info/top_level.txt
doorpi/__init__.py
doorpi/doorpi.py
doorpi/main.py
doorpi/metadata.py
doorpi/action/__init__.py
doorpi/action/base.py
doorpi/action/handler.py
doorpi/action/SingleActions/__init__.py
doorpi/action/SingleActions/call.py
doorpi/action/SingleActions/file_call_value.py
doorpi/action/SingleActions/hangup.py
doorpi/action/SingleActions/ipsrpc_call_value.py
doorpi/action/SingleActions/ipsrpc_setvalue.py
doorpi/action/SingleActions/log.py
doorpi/action/SingleActions/mailto.py
doorpi/action/SingleActions/os_execute.py
doorpi/action/SingleActions/out.py
doorpi/action/SingleActions/out_triggered.py
doorpi/action/SingleActions/pjsip_handle_events.py
doorpi/action/SingleActions/sipphone_calltimeout.py
doorpi/action/SingleActions/sleep.py
doorpi/action/SingleActions/statusfile.py
doorpi/action/SingleActions/statuswatchdog.py
doorpi/action/SingleActions/take_snapshot.py
doorpi/action/SingleActions/time_tick.py
doorpi/action/SingleActions/url_call.py
doorpi/conf/__init__.py
doorpi/conf/backward_compatibility.py
doorpi/conf/config_object.py
doorpi/keyboard/AbstractBaseClass.py
doorpi/keyboard/KeyboardInterface.py
doorpi/keyboard/__init__.py
doorpi/keyboard/from_dummy.py
doorpi/keyboard/from_filesystem.py
doorpi/keyboard/from_gpio.py
doorpi/keyboard/from_piface.py
doorpi/keyboard/from_pn532.py
doorpi/keyboard/from_rdm6300.py
doorpi/keyboard/from_usb_plain.py
doorpi/media/CreateDialTone.py
doorpi/media/__init__.py
doorpi/sipphone/AbstractBaseClass.py
doorpi/sipphone/SipphoneInterface.py
doorpi/sipphone/__init__.py
doorpi/sipphone/from_dummy.py
doorpi/sipphone/from_linphone.py
doorpi/sipphone/from_pjsua.py
doorpi/sipphone/linphone_lib/CallBacks.py
doorpi/sipphone/linphone_lib/Player.py
doorpi/sipphone/linphone_lib/Recorder.py
doorpi/sipphone/linphone_lib/__init__.py
doorpi/sipphone/pjsua_lib/Config.py
doorpi/sipphone/pjsua_lib/Player.py
doorpi/sipphone/pjsua_lib/Recorder.py
doorpi/sipphone/pjsua_lib/SipPhoneAccountCallBack.py
