Metadata-Version: 2.0
Name: DoorPi
Version: 2.5.1
Summary: provide intercomstation to the doorstation by VoIP
Home-page: https://github.com/motom001/DoorPi
Author: Thomas Meissner
Author-email: motom001@gmail.com
License: CC BY-NC 4.0
Keywords: intercom,VoIP,doorstation,home automation,IoT
Platform: any
Classifier: Development Status :: 5 - Production/Stable
Classifier: Environment :: Console
Classifier: Intended Audience :: Developers
Classifier: Intended Audience :: End Users/Desktop
Classifier: Intended Audience :: Information Technology
Classifier: Intended Audience :: System Administrators
Classifier: License :: Free for non-commercial use
Classifier: Natural Language :: German
Classifier: Natural Language :: English
Classifier: Operating System :: OS Independent
Classifier: Programming Language :: Python :: 2.7
Classifier: Topic :: Documentation
Classifier: Topic :: Software Development :: Libraries :: Python Modules
Classifier: Topic :: System :: Installation/Setup
Classifier: Topic :: System :: Software Distribution
Classifier: Topic :: Communications :: Internet Phone
Classifier: Topic :: Communications :: Telephony
Classifier: Topic :: Multimedia :: Sound/Audio :: Capture/Recording
Classifier: Topic :: Multimedia :: Video :: Capture
Classifier: Topic :: Multimedia :: Video :: Conversion
Classifier: Topic :: Security
Classifier: Topic :: System :: Emulators
Classifier: Topic :: System :: Filesystems
Classifier: Topic :: System :: Hardware
Classifier: Topic :: Utilities
Requires-Dist: RPi.GPIO (>=0.5.11)
Requires-Dist: picamera (>=1.10)
Requires-Dist: pifacecommon (>=4.1.2)
Requires-Dist: pifacedigitalio (>=3.0.5)
Requires-Dist: pyserial (>=2.7)
Requires-Dist: requests (>=2.7.0)
Requires-Dist: watchdog (>=0.8.3)
